pangea_multipass_langchain/__init__.py
pangea_multipass_langchain/langchain.py
pangea_multipass_langchain/py.typed
pangea_multipass_langchain-0.2.0.dist-info/METADATA
pangea_multipass_langchain-0.2.0.dist-info/WHEEL
pangea_multipass_langchain-0.2.0.dist-info/RECORD
