Metadata-Version: 2.1
Name: pangea-multipass-langchain
Version: 0.2.0
Summary: Pangea Multipass authorization library for LangChain
License: MIT
Author: Apurv Jawle
Author-email: apurv.jawle@pangea.cloud
Requires-Python: >=3.10,<3.13
Classifier: License :: OSI Approved :: MIT License
Classifier: Programming Language :: Python :: 3
Classifier: Programming Language :: Python :: 3.10
Classifier: Programming Language :: Python :: 3.11
Classifier: Programming Language :: Python :: 3.12
Requires-Dist: google-auth-oauthlib (>=1.2.1,<2.0.0)
Requires-Dist: langchain (==0.3.0)
Requires-Dist: langchain-aws (==0.2.1)
Requires-Dist: langchain-community (==0.3.0)
Requires-Dist: pangea-multipass (==0.2.0)
Requires-Dist: pangea-sdk (>=5.1.0,<6.0.0)
